backend/storage.py
django_nextcloud_storage-2024.5.20.dist-info/METADATA
django_nextcloud_storage-2024.5.20.dist-info/WHEEL
django_nextcloud_storage-2024.5.20.dist-info/top_level.txt
django_nextcloud_storage-2024.5.20.dist-info/RECORD
